gcd-module-in-verilog/fsm.v
`timescale 1ns / 1ps
//////////////////////////////////////////////////////////////////////////////////
// Company: 
// Engineer: 
// 
// Create Date: 13.06.2026 11:10:49
// Design Name: 
// Module Name: fsm
// Project Name: 
// Target Devices: 
// Tool Versions: 
// Description: 
// 
// Dependencies: 
// 
// Revision:
// Revision 0.01 - File Created
// Additional Comments:
// 
//////////////////////////////////////////////////////////////////////////////////


module fsm(input clk,lt,gt,eq,start,input [7:0]data_in,output reg finish,lda,ldb,sel_in,sel_a,sel_b);
parameter s0 = 3'b000, s1 = 3'b001, s2 = 3'b010, s3 = 3'b011,s4 = 3'b100, s5 = 3'b101;
reg [2:0] s;
initial s = 0;
always @(posedge clk)
begin
case (s)
s0 : if (start) s<=s1;
s1 : s<=s2;
s2 : begin if (eq) s<=s5 ;
           else if (lt) s <= s3;
           else if (gt) s<=s4;
     end
s3 :  begin if (eq) s<=s5 ;
           else if (lt) s <= s3;
           else if (gt) s<=s4;
       end
s4 : begin if (eq) s<=s5 ;
           else if (lt) s <= s3;
           else if (gt) s<=s4;
       end
s5 : s <= s5;
default : s <= s0;
endcase
end


always @(s)
begin
case (s)
s0 : begin sel_in = 1; lda = 1; ldb = 0 ; finish = 0; end
s1 : begin sel_in = 1; lda = 0; ldb = 1; end
s2 : if (eq) finish = 1;
     else if (gt) begin sel_a = 0; sel_b = 1; sel_in = 0;
     lda = 1; ldb = 0;
     end
     else if (lt) begin sel_a = 1; sel_b = 0; sel_in = 0;
     #1 lda = 0 ; ldb = 1;
     end
s3 : if (eq) finish = 1;
     else if (gt) begin sel_a = 0; sel_b = 1; sel_in = 0;
     lda = 1; ldb = 0;
     end
     else if (lt) begin sel_a = 1; sel_b = 0; sel_in = 0;
     lda = 0 ; ldb = 1;
     end
s4 : if (eq) finish = 1;
     else if (gt) begin sel_a = 0; sel_b = 1; sel_in = 0;
     lda = 1; ldb = 0;
     end
     else if (lt) begin sel_a = 1; sel_b = 0; sel_in = 0;
     lda = 0 ; ldb = 1;
     end
s5 : begin finish = 1; sel_a = 0; sel_b = 0;  lda = 0; ldb = 0; end
default : begin lda = 0; ldb = 0; end
endcase
end
endmodule

gcd-module-in-verilog/mux.v
`timescale 1ns / 1ps
module mux(input [7:0] x, input [7:0] y , output [7:0] z, input sel);
assign z = sel ? y : x;
endmodule

gcd-module-in-verilog/sub.v
`timescale 1ns / 1ps

module subt(input [7:0] x , y , output reg [7:0] z);
always @(*)
z  = x - y;
endmodule

gcd-module-in-verilog/comp.v
`timescale 1ns / 1ps

module comp(input [7:0] x, input [7:0] y,output lt,gt,eq);
assign lt = x<y;
assign gt =  x>y;
assign eq = x == y ;

endmodule

gcd-module-in-verilog/pipo.v
`timescale 1ns / 1ps

module pipo(input clk,input load, input [7:0] x, output reg [7:0] z);
always @(posedge clk)
if (load)
z <= x;

endmodule

gcd-module-in-verilog/data_path.v
`timescale 1ns / 1ps

module data_path(input clk,lda,ldb,sel_a,sel_b,sel_in,output gt,eq,lt,input [7:0] data_in);
wire [7:0] a,b;
wire [7:0] bus;
wire [7:0] ma,mb,mc,cout;

pipo p1 (.load(lda),.x(bus),.z(a),.clk(clk));
pipo p2 (.load(ldb),.clk(clk),.x(bus),.z(b));
mux ma1 (.sel(sel_a),.x(a),.y(b),.z(ma));
mux mb1 (.sel(sel_b),.x(a),.y(b),.z(mb));
comp c (.x(a),.y(b),.gt(gt),.lt(lt),.eq(eq));
subt s (.x(ma),.y(mb),.z(cout));
mux mc1 (.sel(sel_in),.x(cout),.y(data_in),.z(bus));

endmodule

gcd-module-in-verilog/tb.v
`timescale 1ns / 1ps


module tb;
reg [7:0] data_in;
reg start,clk;
wire finish;

data_path dp (clk,lda,ldb,sel_a,sel_b,sel_in,gt,eq,lt,data_in);
fsm f(clk,lt,gt,eq,start,data_in,finish,lda,ldb,sel_in,sel_a,sel_b);

initial 
begin
clk = 0;
#5;
start = 1;
#300;
$finish;
end

always #5 clk = ~clk;

initial 
begin
$monitor("t=%0t state=%b lda=%b ldb=%b A=%d B=%d",
         $time,f.s,lda,ldb,dp.a,dp.b);
$dumpfile("tb.vcd");
$dumpvars(0,tb);
end

initial 
begin
data_in = 143;
#10 data_in = 78;
end



endmodule

gcd-module-in-verilog/tb.vcd
$date
	Sun Jun 14 07:06:55 2026
$end
$version
	Icarus Verilog
$end
$timescale
	1ps
$end
$scope module tb $end
$var wire 1 ! sel_in $end
$var wire 1 " sel_b $end
$var wire 1 # sel_a $end
$var wire 1 $ lt $end
$var wire 1 % ldb $end
$var wire 1 & lda $end
$var wire 1 ' gt $end
$var wire 1 ( finish $end
$var wire 1 ) eq $end
$var reg 1 * clk $end
$var reg 8 + data_in [7:0] $end
$var reg 1 , start $end
$scope module dp $end
$var wire 1 * clk $end
$var wire 8 - data_in [7:0] $end
$var wire 1 ! sel_in $end
$var wire 1 " sel_b $end
$var wire 1 # sel_a $end
$var wire 8 . mb [7:0] $end
$var wire 8 / ma [7:0] $end
$var wire 1 $ lt $end
$var wire 1 % ldb $end
$var wire 1 & lda $end
$var wire 1 ' gt $end
$var wire 1 ) eq $end
$var wire 8 0 cout [7:0] $end
$var wire 8 1 bus [7:0] $end
$var wire 8 2 b [7:0] $end
$var wire 8 3 a [7:0] $end
$scope module c $end
$var wire 8 4 y [7:0] $end
$var wire 8 5 x [7:0] $end
$var wire 1 $ lt $end
$var wire 1 ' gt $end
$var wire 1 ) eq $end
$upscope $end
$scope module ma1 $end
$var wire 8 6 z [7:0] $end
$var wire 8 7 y [7:0] $end
$var wire 8 8 x [7:0] $end
$var wire 1 # sel $end
$upscope $end
$scope module mb1 $end
$var wire 8 9 z [7:0] $end
$var wire 8 : y [7:0] $end
$var wire 8 ; x [7:0] $end
$var wire 1 " sel $end
$upscope $end
$scope module mc1 $end
$var wire 8 < y [7:0] $end
$var wire 8 = z [7:0] $end
$var wire 8 > x [7:0] $end
$var wire 1 ! sel $end
$upscope $end
$scope module p1 $end
$var wire 1 * clk $end
$var wire 8 ? x [7:0] $end
$var wire 1 & load $end
$var reg 8 @ z [7:0] $end
$upscope $end
$scope module p2 $end
$var wire 1 * clk $end
$var wire 8 A x [7:0] $end
$var wire 1 % load $end
$var reg 8 B z [7:0] $end
$upscope $end
$scope module s $end
$var wire 8 C x [7:0] $end
$var wire 8 D y [7:0] $end
$var reg 8 E z [7:0] $end
$upscope $end
$upscope $end
$scope module f $end
$var wire 1 * clk $end
$var wire 8 F data_in [7:0] $end
$var wire 1 ) eq $end
$var wire 1 ' gt $end
$var wire 1 $ lt $end
$var wire 1 , start $end
$var reg 1 ( finish $end
$var reg 1 & lda $end
$var reg 1 % ldb $end
$var reg 3 G s [2:0] $end
$var reg 1 # sel_a $end
$var reg 1 " sel_b $end
$var reg 1 ! sel_in $end
$upscope $end
$upscope $end
$enddefinitions $end
#0
$dumpvars
b0 G
b10001111 F
bx E
bx D
bx C
bx B
b10001111 A
bx @
b10001111 ?
bx >
b10001111 =
b10001111 <
bx ;
bx :
bx 9
bx 8
bx 7
bx 6
bx 5
bx 4
bx 3
bx 2
b10001111 1
bx 0
bx /
bx .
b10001111 -
x,
b10001111 +
0*
x)
0(
x'
1&
0%
x$
x#
x"
1!
$end
#5000
1%
0&
b10001111 3
b10001111 5
b10001111 8
b10001111 ;
b10001111 @
b1 G
1*
1,
#10000
b1001110 1
b1001110 =
b1001110 ?
b1001110 A
0*
b1001110 +
b1001110 -
b1001110 <
b1001110 F
#15000
b1000001 0
b1000001 >
b1000001 E
b1000001 1
b1000001 =
b1000001 ?
b1000001 A
0%
1&
0!
1"
0#
b1001110 .
b1001110 9
b1001110 D
b10001111 /
b10001111 6
b10001111 C
b10 G
0)
1'
0$
b1001110 2
b1001110 4
b1001110 7
b1001110 :
b1001110 B
1*
#20000
0*
#25000
b1101 1
b1101 =
b1101 ?
b1101 A
b1101 0
b1101 >
b1101 E
b1000001 .
b1000001 9
b1000001 D
b1001110 /
b1001110 6
b1001110 C
1%
0&
0"
1#
0'
1$
b1000001 3
b1000001 5
b1000001 8
b1000001 ;
b1000001 @
b100 G
1*
#30000
0*
#35000
b110100 1
b110100 =
b110100 ?
b110100 A
b1101 .
b1101 9
b1101 D
b110100 0
b110100 >
b110100 E
0%
1&
1"
0#
b1000001 /
b1000001 6
b1000001 C
b11 G
1'
0$
b1101 2
b1101 4
b1101 7
b1101 :
b1101 B
1*
#40000
0*
#45000
b100111 1
b100111 =
b100111 ?
b100111 A
b100111 0
b100111 >
b100111 E
b110100 /
b110100 6
b110100 C
b110100 3
b110100 5
b110100 8
b110100 ;
b110100 @
b100 G
1*
#50000
0*
#55000
b11010 1
b11010 =
b11010 ?
b11010 A
b11010 0
b11010 >
b11010 E
b100111 /
b100111 6
b100111 C
b100111 3
b100111 5
b100111 8
b100111 ;
b100111 @
1*
#60000
0*
#65000
b1101 1
b1101 =
b1101 ?
b1101 A
b1101 0
b1101 >
b1101 E
b11010 /
b11010 6
b11010 C
b11010 3
b11010 5
b11010 8
b11010 ;
b11010 @
1*
#70000
0*
#75000
b0 1
b0 =
b0 ?
b0 A
b0 0
b0 >
b0 E
b1101 /
b1101 6
b1101 C
1)
0'
b1101 3
b1101 5
b1101 8
b1101 ;
b1101 @
1*
#80000
0*
#85000
b0 .
b0 9
b0 D
b0 /
b0 6
b0 C
0&
0"
1(
0)
1$
b0 3
b0 5
b0 8
b0 ;
b0 @
b101 G
1*
